<Properties StartupConfiguration="{885887EC-EACD-418A-A170-48C4153AEC55}|Default">
  <MonoDevelop.Ide.ItemProperties.ALlgoDataStructureProject PreferredExecutionTarget="MonoDevelop.Default" />
  <MonoDevelop.Ide.Workbench ActiveDocument="Program.cs">
    <Files>
      <File FileName="Program.cs" Line="18" Column="16" />
      <File FileName="DataStructure/HashTable.cs" />
    </Files>
    <Pads>
      <Pad Id="ProjectPad">
        <State name="__root__">
          <Node name="ALlgoDataStructureProject" expanded="True">
            <Node name="ALlgoDataStructureProject" expanded="True" selected="True" />
          </Node>
        </State>
      </Pad>
    </Pads>
  </MonoDevelop.Ide.Workbench>
  <MonoDevelop.Ide.DebuggingService.PinnedWatches />
  <MonoDevelop.Ide.Workspace ActiveConfiguration="Debug" />
  <MonoDevelop.Ide.DebuggingService.Breakpoints>
    <BreakpointStore />
  </MonoDevelop.Ide.DebuggingService.Breakpoints>
  <MultiItemStartupConfigurations />
</Properties>